[{"id":1,"name":"猕猴桃","info":"又大又甜5","price":"25","img":"https://timgsa.baidu.com/timg?image&quality=80&size=b9999_10000&sec=1543912633202&di=35e24c2532a018f393f6330ee321373b&imgtype=0&src=http%3A%2F%2Fimg1.sc115.com%2Fuploads%2Fsc%2Fjpg%2FHD%2F33%2F3979.jpg"},{"id":2,"name":"西瓜","info":"又大又甜6","price":"20","img":"http://pic40.photophoto.cn/20160826/1155115709038224_b.jpg"},{"id":3,"name":"柠檬","info":"又大又甜8","price":35,"img":"http://pic40.photophoto.cn/20160826/1155115709038224_b.jpg"},{"id":4,"name":"葡萄","info":"又大又甜9","price":35,"img":"http://pic40.photophoto.cn/20160826/1155115709038224_b.jpg"},{"id":5,"name":"山竹","info":"又大又甜10","price":35,"img":"http://pic40.photophoto.cn/20160826/1155115709038224_b.jpg"},{"id":6,"name":"圣女果11","info":"又大又甜","price":35,"img":"http://pic40.photophoto.cn/20160826/1155115709038224_b.jpg"},{"id":7,"name":"奶茶","info":"又大又甜6","price":"28","img":"nainainainainainainaichachachacha"}]